INSTALL.md
LICENSE
MANIFEST.in
NEWS
README.md
s3cmd
s3cmd.1
setup.cfg
setup.py
S3/ACL.py
S3/AccessLog.py
S3/BaseUtils.py
S3/BidirMap.py
S3/CloudFront.py
S3/Config.py
S3/ConnMan.py
S3/Crypto.py
S3/Custom_httplib27.py
S3/Custom_httplib3x.py
S3/Exceptions.py
S3/ExitCodes.py
S3/FileDict.py
S3/FileLists.py
S3/HashCache.py
S3/MultiPart.py
S3/PkgInfo.py
S3/Progress.py
S3/S3.py
S3/S3Uri.py
S3/SortedDict.py
S3/Utils.py
S3/__init__.py
mbh_s3tool.egg-info/PKG-INFO
mbh_s3tool.egg-info/SOURCES.txt
mbh_s3tool.egg-info/dependency_links.txt
mbh_s3tool.egg-info/requires.txt
mbh_s3tool.egg-info/top_level.txt